yt_dlp_plugins/extractor/youmaker.py
ytdlp_youmaker-2023.12.27.dist-info/LICENSE
ytdlp_youmaker-2023.12.27.dist-info/METADATA
ytdlp_youmaker-2023.12.27.dist-info/WHEEL
ytdlp_youmaker-2023.12.27.dist-info/top_level.txt
ytdlp_youmaker-2023.12.27.dist-info/RECORD
